{
  "experiment_id": "dm_catboost_optuna_v3",
  "disease": "DM",
  "target_col": "당뇨유병",
  "dataset_name": "hn_all",
  "model_type": "catboost",
  "experiment_type": "optuna",
  "feature_set_name": "dm_fe_v3",
  "fe_keys": ["age_bin", "bmi_bin", "family_sum", "bmi_x_age"],
  "n_features": 38,
  "recall_min": 0.87,
  "n_splits": 5,
  "n_trials": 50,
  "seed": 42,
  "threshold": 0.44,
  "best_params": {
    "iterations": 427,
    "learning_rate": 0.02884897588823726,
    "depth": 5,
    "l2_leaf_reg": 4.504403807882317,
    "bagging_temperature": 0.16590134861646655,
    "random_strength": 0.9331797514790412
  },
  "metrics": {
    "auc": 0.8103,
    "recall": 0.8679,
    "precision": 0.3951,
    "f1": 0.5430
  },
  "output_dir": "ai_worker/ml/CAT18~24/outputs/optuna_DM_FE_v3",
  "script": "ai_worker/ml/CAT18~24/CatBoost_Optuna_DM_FE_v3.py",
  "status": "final",
  "note": "DM 최종 모델. CatBoost Optuna v3. 양성비율 23.6% 구조적 한계로 F1 0.54 수준이 상한. FE v4 상호작용 피처 추가 실험 → 효과 없음 확인."
}
